{
  "version": "1.1.0",
  "flags": {},
  "shapes": [
    {
      "label": "basket",
      "text": "",
      "points": [
        [
          201.2834224598931,
          218.3422459893048
        ],
        [
          176.68449197860966,
          310.85561497326205
        ],
        [
          131.76470588235298,
          454.1711229946524
        ],
        [
          134.43850267379685,
          469.14438502673795
        ],
        [
          431.2299465240642,
          458.44919786096256
        ],
        [
          440.3208556149733,
          445.6149732620321
        ],
        [
          376.6844919786097,
          214.06417112299465
        ],
        [
          368.66310160427815,
          209.25133689839572
        ],
        [
          210.37433155080217,
          214.59893048128342
        ]
      ],
      "group_id": null,
      "shape_type": "polygon",
      "flags": {}
    }
  ],
  "imagePath": "..\\images\\40.png",
  "imageData": null,
  "imageHeight": 480,
  "imageWidth": 640
}